spark_frame/__init__.py
spark_frame/conf.py
spark_frame/data_diff/__init__.py
spark_frame/data_diff/compare_dataframes_impl.py
spark_frame/data_diff/diff_format_options.py
spark_frame/data_diff/diff_per_col.py
spark_frame/data_diff/diff_result.py
spark_frame/data_diff/diff_result_analyzer.py
spark_frame/data_diff/diff_result_summary.py
spark_frame/data_diff/diff_stats.py
spark_frame/data_diff/export.py
spark_frame/data_diff/package.py
spark_frame/data_diff/sample.py
spark_frame/data_diff/schema_diff.py
spark_frame/data_diff/special_characters.py
spark_frame/data_type_utils.py
spark_frame/examples/__init__.py
spark_frame/examples/flatten_unflatten.py
spark_frame/examples/reference_nested.py
spark_frame/examples/working_with_json.py
spark_frame/examples/working_with_nested_data.py
spark_frame/exceptions.py
spark_frame/field_utils.py
spark_frame/filesystem.py
spark_frame/fp/README.md
spark_frame/fp/__init__.py
spark_frame/fp/higher_order.py
spark_frame/fp/package.py
spark_frame/fp/printable_function.py
spark_frame/functions.py
spark_frame/graph.py
spark_frame/graph_impl/__init__.py
spark_frame/graph_impl/ascending_forest_traversal.py
spark_frame/nested.py
spark_frame/nested_functions.py
spark_frame/nested_functions_impl/__init__.py
spark_frame/nested_functions_impl/aggregate.py
spark_frame/nested_functions_impl/average.py
spark_frame/nested_functions_impl/sum.py
spark_frame/nested_impl/__init__.py
spark_frame/nested_impl/fields.py
spark_frame/nested_impl/package.py
spark_frame/nested_impl/print_schema.py
spark_frame/nested_impl/schema_string.py
spark_frame/nested_impl/select_impl.py
spark_frame/nested_impl/unnest_all_fields.py
spark_frame/nested_impl/unnest_field.py
spark_frame/nested_impl/with_fields.py
spark_frame/py.typed
spark_frame/schema_utils.py
spark_frame/transformations.py
spark_frame/transformations_impl/__init__.py
spark_frame/transformations_impl/analyze.py
spark_frame/transformations_impl/analyze_aggs.py
spark_frame-0.5.2.dist-info/LICENSE
spark_frame-0.5.2.dist-info/WHEEL
spark_frame-0.5.2.dist-info/METADATA
spark_frame-0.5.2.dist-info/RECORD
