Metadata-Version: 2.1
Name: spark-frame
Version: 0.5.2
Summary: A library containing various utility functions for playing with PySpark DataFrames
Home-page: https://github.com/FurcyPin/spark-frame
License: Apache-2.0
Keywords: Spark,PySpark,DataFrame
Author: FurcyPin
Requires-Python: >=3.8.1,<3.13
Classifier: License :: OSI Approved :: Apache Software License
Classifier: Programming Language :: Python :: 3
Classifier: Programming Language :: Python :: 3.9
Classifier: Programming Language :: Python :: 3.10
Classifier: Programming Language :: Python :: 3.11
Requires-Dist: pip (>=24.0.0,<25.0.0)
Project-URL: Repository, https://github.com/FurcyPin/spark-frame
